tva/__init__.py
tva/logging/__init__.py
tva/logging/logging.py
tva/parser/__init__.py
tva/parser/parser.py
tva/postgres/__init__.py
tva/postgres/funcs.py
tva-0.1.1.dist-info/METADATA
tva-0.1.1.dist-info/WHEEL
tva-0.1.1.dist-info/RECORD
